odoo10_addon_mail_force_queue-10.0.0.2.0-py2.7-nspkg.pth
odoo/addons/mail_force_queue/README.rst
odoo/addons/mail_force_queue/__init__.py
odoo/addons/mail_force_queue/__manifest__.py
odoo/addons/mail_force_queue/models/__init__.py
odoo/addons/mail_force_queue/models/mail_message.py
odoo/addons/mail_force_queue/models/res_company.py
odoo/addons/mail_force_queue/models/res_config.py
odoo/addons/mail_force_queue/static/description/icon.png
odoo/addons/mail_force_queue/tests/__init__.py
odoo/addons/mail_force_queue/tests/test_mail_notification.py
odoo/addons/mail_force_queue/views/res_config_view.xml
odoo10_addon_mail_force_queue-10.0.0.2.0.dist-info/DESCRIPTION.rst
odoo10_addon_mail_force_queue-10.0.0.2.0.dist-info/METADATA
odoo10_addon_mail_force_queue-10.0.0.2.0.dist-info/RECORD
odoo10_addon_mail_force_queue-10.0.0.2.0.dist-info/WHEEL
odoo10_addon_mail_force_queue-10.0.0.2.0.dist-info/metadata.json
odoo10_addon_mail_force_queue-10.0.0.2.0.dist-info/namespace_packages.txt
odoo10_addon_mail_force_queue-10.0.0.2.0.dist-info/top_level.txt
