Metadata-Version: 2.0
Name: odoo10-addon-mail-force-queue
Version: 10.0.0.2.0
Summary: Force outgoing emails to be queued
Home-page: https://github.com/OCA/social
Author: Agile Business Group, Odoo Community Association (OCA)
Author-email: support@odoo-community.org
License: LGPL-3
Platform: UNKNOWN
Classifier: Programming Language :: Python
Classifier: Framework :: Odoo
Classifier: License :: OSI Approved :: GNU Lesser General Public License v3 (LGPLv3)
Requires-Python: ~=2.7
Requires-Dist: odoo (<10.1dev,>=10.0)
